NarrowBand-0.2.1.dist-info/METADATA
NarrowBand-0.2.1.dist-info/RECORD
NarrowBand-0.2.1.dist-info/WHEEL
NarrowBand-0.2.1.dist-info/top_level.txt
narrowband/__init__.py
narrowband/narrowbandcore.py
