Metadata-Version: 2.1
Name: NarrowBand
Version: 0.2.1
Summary: NarrowBand library
Home-page: http://pypi.python.org/pypi/NarrowBand/
Author: Dominik Fehr
Author-email: dominik@fe.hr
Maintainer: Andreas Schmidt
Maintainer-email: andreas.schmidt@cassini.de
License: Creative Commons Attribution-NonCommercial-ShareAlike 4.0 International Public License
Keywords: nb1 m1 nb-iot iot lte narrowband cat-nb1 cat-m1
Platform: UNKNOWN
Classifier: Development Status :: 2 - Pre-Alpha
Classifier: Intended Audience :: Developers
Classifier: Intended Audience :: Information Technology
Classifier: Intended Audience :: Science/Research
Classifier: Intended Audience :: Telecommunications Industry
Classifier: License :: Other/Proprietary License
Classifier: Programming Language :: Python
Requires-Dist: pyserial (>=3.4)
